pentesterhelper/__init__.py
pentesterhelper/pentesterhelper.py
pentesterhelper-0.0.1.dist-info/METADATA
pentesterhelper-0.0.1.dist-info/WHEEL
pentesterhelper-0.0.1.dist-info/top_level.txt
pentesterhelper-0.0.1.dist-info/RECORD
