Metadata-Version: 2.1
Name: pentesterhelper
Version: 0.0.1
Summary: Automation of finding Static Website Vulnerability
Author: Kr Rathod
Author-email: Kr Rathod <thekrrathod@gmail.com>
Project-URL: Homepage, https://github.com/pentesterhelper/pentesterhelper.github.io/
Project-URL: Bug Tracker, https://github.com/pentesterhelper/pentesterhelper.github.io/issues
Classifier: Programming Language :: Python :: 3
Classifier: License :: OSI Approved :: MIT License
Classifier: Operating System :: OS Independent
Requires-Python: >=3.3.3
Requires-Dist: termcolor
Requires-Dist: pyfiglet
